{"version":1,"resource":"file:///home/david/.zshrc","entries":[{"id":"KpXE","timestamp":1765485564489},{"id":"O9Yf","source":"undoRedo.source","timestamp":1765485654371},{"id":"IR4f","timestamp":1765485742134},{"id":"a5uh","source":"undoRedo.source","timestamp":1765485792099},{"id":"Dt9b","timestamp":1765485851270},{"id":"9pTa","timestamp":1765485866683},{"id":"tPPX","timestamp":1765487116240},{"id":"mnSL","timestamp":1765488863322},{"id":"BzIk","timestamp":1765490832033},{"id":"UGqd","timestamp":1765490998305},{"id":"8Dq9","timestamp":1765491079386},{"id":"Phyj","timestamp":1765491101688},{"id":"I2jU","timestamp":1765491111770},{"id":"UZVB","timestamp":1765491375514},{"id":"8Sos","timestamp":1765491388518},{"id":"EbGi","timestamp":1765491525976},{"id":"oeLz","timestamp":1765493121831},{"id":"q8qJ","source":"undoRedo.source","timestamp":1765493132813},{"id":"MDpW","timestamp":1765493138705}]}